pyshotty/__init__.py
pyshotty/screenshot.py
pyshotty-0.0.3.5.dist-info/METADATA
pyshotty-0.0.3.5.dist-info/WHEEL
pyshotty-0.0.3.5.dist-info/top_level.txt
pyshotty-0.0.3.5.dist-info/RECORD
