Metadata-Version: 2.1
Name: pyshotty
Version: 0.0.3.5
Summary: Python website screen grabber
Home-page: https://github.com/lewis-morris/pyshotty
Author: Lewis Morris
Author-email: lewism@codeus.co.uk
License: MIT
Platform: UNKNOWN
